[{"id":"bootcampprep","title":"Practical Steps For Success In a Coding Bootcamp","author":{"firstName":"Kaisma","lastName":"Penn-Titley","email":"kpenn.titley@gmail.com"},"pubDate":"2017-09-30","content":"test"},{"id":"bootcampprep2","title":"Practical Steps For Success In a Coding Bootcamp2","author":{"firstName":"Kaisma","lastName":"Penn-Titley","email":"kade.chalwell@gmail.com"},"pubDate":"2017-09-30","content":"test2"},{"id":"bootcampprep3","title":"Practical Steps For Success In a Coding Bootcamp3","author":{"firstName":"Kaisma M","lastName":"Titley","email":"kpenn.titley@gmail.com"},"pubDate":"2017-09-30","content":"test 3"},{"id":"bootcampprep4","title":"Practical Steps For Success In a Coding Bootcamp4","author":{"firstName":"Kaisma M","lastName":"Titley","email":"kpenn.titley@gmail.com"},"pubDate":"2017-09-30","content":"test 5"},{"id":"bootcampprep6","title":"Practical Steps For Success In a Coding Bootcamp6","author":"Kaisma MTitley","pubDate":"2017-09-30","content":"test 6"}]